OpticalRS/Lyzenga1978.py
OpticalRS/__init__.py
OpticalRS/MSExposure.py
OpticalRS/Lyzenga1981.py
OpticalRS/RasterDS.py
OpticalRS/Lyzenga2006.py
OpticalRS/Sagawa2010.py
OpticalRS/OpticalRS.py
OpticalRS/MSDisplay.py
OpticalRS/LandMasking.py
OpticalRS/RasterSubset.py
OpticalRS/ArrayUtils.py
OpticalRS-0.1.0.dist-info/WHEEL
OpticalRS-0.1.0.dist-info/RECORD
OpticalRS-0.1.0.dist-info/metadata.json
OpticalRS-0.1.0.dist-info/DESCRIPTION.rst
OpticalRS-0.1.0.dist-info/METADATA
OpticalRS-0.1.0.dist-info/top_level.txt
