Metadata-Version: 2.0
Name: OpticalRS
Version: 0.1.0
Summary: OpticalRS is a Python implementation of optical remote sensing methods for mapping of submerged habitats.
Home-page: https://github.com/jkibele/OpticalRS
Author: Jared Kibele
Author-email: jkibele@gmail.com
License: BSD
Keywords: OpticalRS
Platform: UNKNOWN
Classifier: Development Status :: 2 - Pre-Alpha
Classifier: Intended Audience :: Developers
Classifier: License :: OSI Approved :: BSD License
Classifier: Natural Language :: English
Classifier: Programming Language :: Python :: 2
Classifier: Programming Language :: Python :: 2.6
Classifier: Programming Language :: Python :: 2.7
Requires-Dist: numpy
Requires-Dist: pandas
Requires-Dist: statsmodels
Requires-Dist: matplotlib
Requires-Dist: scikit-image
Requires-Dist: GDAL
Requires-Dist: geopandas
Requires-Dist: rasterstats
Requires-Dist: scipy
